README.md
printutil.py
setup.py
learncode.egg-info/PKG-INFO
learncode.egg-info/SOURCES.txt
learncode.egg-info/dependency_links.txt
learncode.egg-info/top_level.txt