Metadata-Version: 2.1
Name: learncode
Version: 1.0.2
Summary: a temp learncode use by first.
Home-page: 
Author: yunlk
Author-email: 1188846330@qq.com
